{
    "descriptions": [
        {
            "filename": "1.jpg",
            "folder": "images",
            "size": {
                "nrows": 256,
                "ncols": 256
            },
            "objects": [
                {
                    "name": "signal",
                    "id": 0,
                    "region": {
                        "xmin": 0,
                        "xmax": 255,
                        "ymin": 0,
                        "ymax": 255
                    }
                }
            ]
        }
    ]
}